[
  {
    "type": "Push",
    "script": [
      {
        "page": 1,
        "content": "푸시1"
      },
      {
        "page": 2,
        "content": "푸시2"
      },
      {
        "page": 3,
        "content": "푸시3"
      },
      {
        "page": 4,
        "content": "푸시4"
      }
    ]
  },

  {
    "type": "Speed",
    "script": [
      {
        "page": 1,
        "content": "스피드1"
      },
      {
        "page": 2,
        "content": "스피드2"
      },
      {
        "page": 3,
        "content": "스피드3"
      }
    ]
  },

  {
    "type": "Memory",
    "script": [
      {
        "page": 1,
        "content" : "메모리1"
      },
      {
        "page": 2,
        "content": "메모리2"
      },
      {
        "page": 3,
        "content": "메모리3"
      }
    ]
  }
]